openxlab/__init__.py
openxlab/cli.py
openxlab/config/__init__.py
openxlab/config/version.py
openxlab/demo_cmd/__init__.py
openxlab/model/__init__.py
openxlab/model/clients/__init__.py
openxlab/model/clients/model_client.py
openxlab/model/clients/openapi_client.py
openxlab/model/commands/__init__.py
openxlab/model/commands/create.py
openxlab/model/commands/download.py
openxlab/model/commands/inference.py
openxlab/model/commands/init.py
openxlab/model/commands/list.py
openxlab/model/commands/remove.py
openxlab/model/commands/upload.py
openxlab/model/commands/visibility.py
openxlab/model/common/__init__.py
openxlab/model/common/constants.py
openxlab/model/common/response_dto.py
openxlab/model/handler/__init__.py
openxlab/model/handler/common.py
openxlab/model/handler/create_repository.py
openxlab/model/handler/download_file.py
openxlab/model/handler/model_inference.py
openxlab/model/handler/model_list.py
openxlab/model/handler/query_meta_info.py
openxlab/model/handler/remove_repo_or_file.py
openxlab/model/handler/update_file.py
openxlab/types/__init__.py
openxlab/types/command_type.py
openxlab/utils/__init__.py
openxlab/utils/file.py
openxlab/xlab/__init__.py
digocli-0.0.3.dist-info/METADATA
digocli-0.0.3.dist-info/WHEEL
digocli-0.0.3.dist-info/entry_points.txt
digocli-0.0.3.dist-info/top_level.txt
digocli-0.0.3.dist-info/RECORD
