Metadata-Version: 2.1
Name: digocli
Version: 0.0.3
Summary: digocli
Home-page: https://github.com/xxx/xxxx
Author: Openxlab Contributors
Author-email: myname@example.com
License: Apache License 2.0
Keywords: openxlab,xxxx
Platform: UNKNOWN
Classifier: Development Status :: 3 - Alpha
Requires-Dist: requests (~=2.28.2)
Requires-Dist: tqdm (~=4.65.0)
Requires-Dist: setuptools (~=60.2.0)
Provides-Extra: build
Provides-Extra: optional
Provides-Extra: tests
